gui/__init__.py
gui/configuration_gui.py
gui/step_creation.py
gui_handlers/__init__.py
gui_handlers/configuration_gui/__init__.py
gui_handlers/configuration_gui/buttons/__init__.py
gui_handlers/configuration_gui/buttons/add_url_from_input_button.py
gui_handlers/configuration_gui/buttons/browse_file_button.py
gui_handlers/configuration_gui/buttons/delete_button.py
gui_handlers/configuration_gui/buttons/move_from_listbox_to_listbox_button.py
gui_handlers/configuration_gui/buttons/project_path_scan_urls_button.py
gui_handlers/configuration_gui/buttons/save_url_from_input_button.py
gui_handlers/configuration_gui/listboxes/__init__.py
gui_handlers/configuration_gui/listboxes/change_selected_checkbox.py
gui_handlers/step_creation/__init__.py
gui_handlers/step_creation/buttons/__init__.py
gui_handlers/step_creation/buttons/add_action_button.py
gui_handlers/step_creation/buttons/copy_html_button.py
gui_handlers/step_creation/buttons/create_new_test_button.py
gui_handlers/step_creation/buttons/current_domain_helper_button.py
gui_handlers/step_creation/buttons/delete_action_button.py
gui_handlers/step_creation/buttons/generate_plan_button.py
gui_handlers/step_creation/buttons/load_configuration_button.py
gui_handlers/step_creation/buttons/move_action_arrows_buttons.py
gui_handlers/step_creation/buttons/reload_actions_button.py
gui_handlers/step_creation/buttons/reset_saved_htmls_button.py
gui_handlers/step_creation/buttons/save_changed_xpath_button.py
gui_handlers/step_creation/buttons/save_configuration_button.py
gui_handlers/step_creation/buttons/show_html_button.py
gui_handlers/step_creation/buttons/tag_positions_buttons_check_tag.py
gui_handlers/step_creation/listboxes/__init__.py
gui_handlers/step_creation/listboxes/tag_list_listbox.py
gui_handlers/step_creation/listboxes/todo_actions_and_tag_listboxes.py
gui_handlers/step_creation/listboxes/todo_actions_listbox.py
gui_handlers/step_creation/selects/__init__.py
gui_handlers/step_creation/selects/actions_choice_select.py
pb_testing-0.2.2.dist-info/LICENSE
pb_testing-0.2.2.dist-info/METADATA
pb_testing-0.2.2.dist-info/WHEEL
pb_testing-0.2.2.dist-info/top_level.txt
pb_testing-0.2.2.dist-info/RECORD
