Metadata-Version: 2.1
Name: pb-testing
Version: 0.2.2
Summary: Library for bdd testing
Home-page: https://github.com/me3eh/POM_BiDiDi
Author: Me
Author-email: bociukmeeeh@gmail.com
License: MIT
Project-URL: Bug Tracker, https://github.com/me3eh/POM_BiDiDi/issues
Classifier: Programming Language :: Python :: 3
Classifier: License :: OSI Approved :: MIT License
Classifier: Operating System :: Unix
Requires-Python: >=3.8
License-File: LICENSE
Requires-Dist: bs4 (>=0.0.1)
Requires-Dist: behave (>=1.2.5)
Requires-Dist: PySimpleGUI (>=4.60.4)
Requires-Dist: pyperclip (>=1.8.2)
Requires-Dist: mechanize (>=0.4.8)
Requires-Dist: selenium (>=4.6.0)
Requires-Dist: lxml (>=4.9.1)
